LICENSE
MANIFEST.in
README.md
setup.py
stellar/__init__.py
stellar/__main__.py
stellar/app.py
stellar/command.py
stellar/config.py
stellar/models.py
stellar/operations.py
stellar.egg-info/PKG-INFO
stellar.egg-info/SOURCES.txt
stellar.egg-info/dependency_links.txt
stellar.egg-info/entry_points.txt
stellar.egg-info/not-zip-safe
stellar.egg-info/requires.txt
stellar.egg-info/top_level.txt
tests/test_models.py
tests/test_operations.py
tests/test_starts.py