Metadata-Version: 1.1
Name: stellar
Version: 0.4.5
Summary: stellar is a tool for creating and restoring database snapshots
Home-page: https://github.com/fastmonkeys/stellar
Author: Teemu Kokkonen, Pekka Pöyry
Author-email: teemu@fastmonkeys.com, pekka@fastmonkeys.com
License: BSD
Platform: any
Classifier: Intended Audience :: Developers
Classifier: License :: OSI Approved :: BSD License
Classifier: Operating System :: POSIX
Classifier: Operating System :: Microsoft :: Windows
Classifier: Operating System :: MacOS :: MacOS X
Classifier: Topic :: Utilities
Classifier: Programming Language :: Python :: 2
Classifier: Programming Language :: Python :: 3
Classifier: Topic :: Database
Classifier: Topic :: Software Development :: Version Control
